pulsipip/__init__.py
pulsipip/cli.py
pulsipip-0.1.5.dist-info/entry_points.txt
pulsipip-0.1.5.dist-info/WHEEL
pulsipip-0.1.5.dist-info/METADATA
pulsipip-0.1.5.dist-info/RECORD
