Metadata-Version: 2.1
Name: pulsipip
Version: 0.1.5
Summary: 
Author: catethos
Author-email: cloverethos@gmail.com
Requires-Python: >=3.7,<4.0
Classifier: Programming Language :: Python :: 3
Classifier: Programming Language :: Python :: 3.7
Classifier: Programming Language :: Python :: 3.8
Classifier: Programming Language :: Python :: 3.9
Requires-Dist: boto3 (>=1.17.5,<2.0.0)
Requires-Dist: piphyperd (>=1.9.10,<2.0.0)
Requires-Dist: typer (>=0.3.2,<0.4.0)
